[{"id":1,"product":"Wine - Chablis 2003 Champs","price":"$1.37","inStock":false},
{"id":2,"product":"Juice Peach Nectar","price":"$6.62","inStock":true},
{"id":3,"product":"Muffin Batt - Ban Dream Zero","price":"$0.87","inStock":false},
{"id":4,"product":"Food Colouring - Pink","price":"$5.60","inStock":false},
{"id":5,"product":"Nut - Hazelnut, Whole","price":"$4.38","inStock":true},
{"id":6,"product":"Veal - Nuckle","price":"$5.56","inStock":true},
{"id":7,"product":"Avocado","price":"$6.80","inStock":true},
{"id":8,"product":"Tomato - Tricolor Cherry","price":"$4.22","inStock":false},
{"id":9,"product":"Seabream Whole Farmed","price":"$1.04","inStock":false},
{"id":10,"product":"Steampan - Foil","price":"$9.43","inStock":true},
{"id":11,"product":"Ecolab - Solid Fusion","price":"$4.25","inStock":true},
{"id":12,"product":"Rum - Coconut, Malibu","price":"$2.84","inStock":true},
{"id":13,"product":"Apple - Fuji","price":"$3.79","inStock":true},
{"id":14,"product":"Coriander - Ground","price":"$3.27","inStock":true},
{"id":15,"product":"Banana - Green","price":"$4.28","inStock":false},
{"id":16,"product":"Puree - Mocha","price":"$1.50","inStock":false},
{"id":17,"product":"Scallop - St. Jaques","price":"$7.41","inStock":true},
{"id":18,"product":"Towel Multifold","price":"$5.62","inStock":false},
{"id":19,"product":"Liners - Baking Cups","price":"$9.13","inStock":true},
{"id":20,"product":"Bread Base - Italian","price":"$0.90","inStock":false},
{"id":21,"product":"Guinea Fowl","price":"$6.35","inStock":false},
{"id":22,"product":"Bread Base - Toscano","price":"$5.94","inStock":false},
{"id":23,"product":"Wine - Chateau Timberlay","price":"$7.43","inStock":true},
{"id":24,"product":"Tuna - Canned, Flaked, Light","price":"$9.30","inStock":false},
{"id":25,"product":"Carrots - Mini Red Organic","price":"$5.67","inStock":false},
{"id":26,"product":"Crab - Dungeness, Whole","price":"$8.92","inStock":false},
{"id":27,"product":"Madeira","price":"$2.80","inStock":true},
{"id":28,"product":"Prunes - Pitted","price":"$3.73","inStock":true},
{"id":29,"product":"Pepper - Orange","price":"$6.29","inStock":false},
{"id":30,"product":"Wine - Kwv Chenin Blanc South","price":"$7.71","inStock":false},
{"id":31,"product":"Cleaner - Lime Away","price":"$7.85","inStock":false},
{"id":32,"product":"Wine - Chianti Classico Riserva","price":"$7.89","inStock":true},
{"id":33,"product":"Anchovy In Oil","price":"$7.53","inStock":false},
{"id":34,"product":"Wine - Segura Viudas Aria Brut","price":"$1.32","inStock":true},
{"id":35,"product":"Cheese - Parmesan Cubes","price":"$1.05","inStock":true},
{"id":36,"product":"Initation Crab Meat","price":"$3.62","inStock":true},
{"id":37,"product":"Rappini - Andy Boy","price":"$2.81","inStock":true},
{"id":38,"product":"Hot Choc Vending","price":"$7.99","inStock":false},
{"id":39,"product":"Barramundi","price":"$1.40","inStock":true},
{"id":40,"product":"Vinegar - Balsamic, White","price":"$2.52","inStock":true},
{"id":41,"product":"Wine - Red Oakridge Merlot","price":"$4.27","inStock":true},
{"id":42,"product":"Cheese - Ricotta","price":"$2.60","inStock":true},
{"id":43,"product":"Turkey - Breast, Boneless Sk On","price":"$3.69","inStock":true},
{"id":44,"product":"Country Roll","price":"$1.85","inStock":false},
{"id":45,"product":"Truffle Cups - Brown","price":"$2.97","inStock":false},
{"id":46,"product":"Pastry - Butterscotch Baked","price":"$5.04","inStock":true},
{"id":47,"product":"Jello - Assorted","price":"$0.15","inStock":false},
{"id":48,"product":"Puff Pastry - Slab","price":"$9.87","inStock":true},
{"id":49,"product":"Brandy - Orange, Mc Guiness","price":"$7.08","inStock":true},
{"id":50,"product":"Broom - Corn","price":"$8.56","inStock":false},
{"id":51,"product":"Red Currants","price":"$8.13","inStock":true},
{"id":52,"product":"Wine - Marlbourough Sauv Blanc","price":"$7.65","inStock":true},
{"id":53,"product":"Nut - Walnut, Chopped","price":"$2.48","inStock":true},
{"id":54,"product":"Liners - Baking Cups","price":"$7.26","inStock":true},
{"id":55,"product":"Doilies - 12, Paper","price":"$0.49","inStock":true},
{"id":56,"product":"Beer - True North Strong Ale","price":"$2.25","inStock":true},
{"id":57,"product":"Pasta - Agnolotti - Butternut","price":"$1.99","inStock":true},
{"id":58,"product":"Steampan - Half Size Shallow","price":"$0.43","inStock":true},
{"id":59,"product":"Chocolate - Pistoles, Lactee, Milk","price":"$1.88","inStock":false},
{"id":60,"product":"Table Cloth 91x91 Colour","price":"$3.28","inStock":false},
{"id":61,"product":"Eel - Smoked","price":"$2.01","inStock":true},
{"id":62,"product":"Russian Prince","price":"$3.05","inStock":true},
{"id":63,"product":"Pork Ham Prager","price":"$0.81","inStock":true},
{"id":64,"product":"Cheese - Manchego, Spanish","price":"$0.86","inStock":false},
{"id":65,"product":"Star Anise, Whole","price":"$9.15","inStock":true},
{"id":66,"product":"Coffee - Frthy Coffee Crisp","price":"$1.94","inStock":true},
{"id":67,"product":"The Pop Shoppe Pinapple","price":"$2.73","inStock":false},
{"id":68,"product":"Bread - Italian Corn Meal Poly","price":"$3.24","inStock":false},
{"id":69,"product":"Melon - Watermelon, Seedless","price":"$6.99","inStock":true},
{"id":70,"product":"Rabbit - Legs","price":"$1.42","inStock":false},
{"id":71,"product":"Squid - U 5","price":"$8.85","inStock":true},
{"id":72,"product":"Rabbit - Saddles","price":"$3.33","inStock":false},
{"id":73,"product":"Beer - Labatt Blue","price":"$9.33","inStock":true},
{"id":74,"product":"Wine - Red, Harrow Estates, Cab","price":"$6.81","inStock":true},
{"id":75,"product":"Chips - Potato Jalapeno","price":"$5.72","inStock":false},
{"id":76,"product":"Pear - Asian","price":"$5.38","inStock":false},
{"id":77,"product":"Cake - Dulce De Leche","price":"$8.84","inStock":false},
{"id":78,"product":"Potatoes - Fingerling 4 Oz","price":"$9.62","inStock":false},
{"id":79,"product":"Nantucket Cranberry Juice","price":"$0.66","inStock":true},
{"id":80,"product":"Chocolate - Semi Sweet, Calets","price":"$9.02","inStock":false},
{"id":81,"product":"Shrimp - 21/25, Peel And Deviened","price":"$5.36","inStock":false},
{"id":82,"product":"Foil Cont Round","price":"$5.58","inStock":false},
{"id":83,"product":"Plate - Foam, Bread And Butter","price":"$6.53","inStock":true},
{"id":84,"product":"Creme De Menth - White","price":"$8.25","inStock":false},
{"id":85,"product":"Sprouts - Corn","price":"$5.63","inStock":true},
{"id":86,"product":"Mushroom - Crimini","price":"$2.93","inStock":false},
{"id":87,"product":"Mahi Mahi","price":"$1.65","inStock":false},
{"id":88,"product":"Gherkin - Sour","price":"$8.60","inStock":true},
{"id":89,"product":"Yogurt - Banana, 175 Gr","price":"$7.89","inStock":false},
{"id":90,"product":"Cranberries - Fresh","price":"$4.68","inStock":true},
{"id":91,"product":"Salmon Steak - Cohoe 6 Oz","price":"$8.30","inStock":true},
{"id":92,"product":"Beans - Soya Bean","price":"$0.70","inStock":false},
{"id":93,"product":"Chinese Lemon Pork","price":"$1.80","inStock":true},
{"id":94,"product":"Lobster - Baby, Boiled","price":"$1.89","inStock":true},
{"id":95,"product":"Pear - Packum","price":"$7.07","inStock":false},
{"id":96,"product":"Snapple Lemon Tea","price":"$2.24","inStock":true},
{"id":97,"product":"Shrimp - 16/20, Iqf, Shell On","price":"$5.28","inStock":false},
{"id":98,"product":"Truffle Shells - White Chocolate","price":"$4.94","inStock":true},
{"id":99,"product":"Nantucket - Orange Mango Cktl","price":"$5.99","inStock":true},
{"id":100,"product":"Butter - Salted, Micro","price":"$4.17","inStock":true}]